{
  "status": 0,
  "result": [
    {
      "createdById": "0055j000004hAriAAE",
      "createdByName": "Subhash Panchani",
      "createdDate": "2023-07-14T03:49:30.000Z",
      "fileName": "components/SitePoweredBy.component",
      "fullName": "SitePoweredBy",
      "id": "0995j0000004OmqAAE",
      "lastModifiedById": "0055j000004hAriAAE",
      "lastModifiedByName": "Subhash Panchani",
      "lastModifiedDate": "2023-07-14T03:49:30.000Z",
      "manageableState": "unmanaged",
      "type": "ApexComponent"
    },
    {
      "createdById": "0055j000004hAriAAE",
      "createdByName": "Subhash Panchani",
      "createdDate": "2022-02-09T14:35:17.000Z",
      "fileName": "components/sfcma__emailNotificationLogo.component",
      "fullName": "sfcma__emailNotificationLogo",
      "id": "0995j000000YArsAAG",
      "lastModifiedById": "0055j000004hAriAAE",
      "lastModifiedByName": "Subhash Panchani",
      "lastModifiedDate": "2022-02-09T14:35:17.000Z",
      "manageableState": "installed",
      "namespacePrefix": "sfcma",
      "type": "ApexComponent"
    },
    {
      "createdById": "0055j000004hAriAAE",
      "createdByName": "Subhash Panchani",
      "createdDate": "2022-02-09T14:35:17.000Z",
      "fileName": "components/sfcma__emailNotificationFooter.component",
      "fullName": "sfcma__emailNotificationFooter",
      "id": "0995j000000YArrAAG",
      "lastModifiedById": "0055j000004hAriAAE",
      "lastModifiedByName": "Subhash Panchani",
      "lastModifiedDate": "2022-02-09T14:35:17.000Z",
      "manageableState": "installed",
      "namespacePrefix": "sfcma",
      "type": "ApexComponent"
    },
    {
      "createdById": "0055j000004hAriAAE",
      "createdByName": "Subhash Panchani",
      "createdDate": "2022-02-09T14:35:17.000Z",
      "fileName": "components/sfcma__emailNotificationMessageWarning.component",
      "fullName": "sfcma__emailNotificationMessageWarning",
      "id": "0995j000000YArtAAG",
      "lastModifiedById": "0055j000004hAriAAE",
      "lastModifiedByName": "Subhash Panchani",
      "lastModifiedDate": "2022-02-09T14:35:17.000Z",
      "manageableState": "installed",
      "namespacePrefix": "sfcma",
      "type": "ApexComponent"
    },
    {
      "createdById": "0055j000004hAriAAE",
      "createdByName": "Subhash Panchani",
      "createdDate": "2025-05-08T05:04:02.000Z",
      "fileName": "components/signature__SignatureExperiences.component",
      "fullName": "signature__SignatureExperiences",
      "id": "099Ip0000004D6oIAE",
      "lastModifiedById": "0055j000004hAriAAE",
      "lastModifiedByName": "Subhash Panchani",
      "lastModifiedDate": "2025-05-08T05:05:53.000Z",
      "manageableState": "installed",
      "namespacePrefix": "signature",
      "type": "ApexComponent"
    },
    {
      "createdById": "0055j000004hAriAAE",
      "createdByName": "Subhash Panchani",
      "createdDate": "2025-05-08T05:04:02.000Z",
      "fileName": "components/signature__SignatureForm.component",
      "fullName": "signature__SignatureForm",
      "id": "099Ip0000004D6pIAE",
      "lastModifiedById": "0055j000004hAriAAE",
      "lastModifiedByName": "Subhash Panchani",
      "lastModifiedDate": "2025-05-08T05:05:55.000Z",
      "manageableState": "installed",
      "namespacePrefix": "signature",
      "type": "ApexComponent"
    },
    {
      "createdById": "0055j000004hAriAAE",
      "createdByName": "Subhash Panchani",
      "createdDate": "2025-06-12T09:23:54.000Z",
      "fileName": "components/et4ae5__dynamicSendPreview.component",
      "fullName": "et4ae5__dynamicSendPreview",
      "id": "099Ip0000004D8UIAU",
      "lastModifiedById": "0055j000004hAriAAE",
      "lastModifiedByName": "Subhash Panchani",
      "lastModifiedDate": "2025-06-12T09:26:01.000Z",
      "manageableState": "installed",
      "namespacePrefix": "et4ae5",
      "type": "ApexComponent"
    },
    {
      "createdById": "0055j000004hAriAAE",
      "createdByName": "Subhash Panchani",
      "createdDate": "2025-05-08T05:04:02.000Z",
      "fileName": "components/signature__ImportExperiences.component",
      "fullName": "signature__ImportExperiences",
      "id": "099Ip0000004D6mIAE",
      "lastModifiedById": "0055j000004hAriAAE",
      "lastModifiedByName": "Subhash Panchani",
      "lastModifiedDate": "2025-05-08T05:05:52.000Z",
      "manageableState": "installed",
      "namespacePrefix": "signature",
      "type": "ApexComponent"
    },
    {
      "createdById": "0055j000004hAriAAE",
      "createdByName": "Subhash Panchani",
      "createdDate": "2023-07-14T03:49:31.000Z",
      "fileName": "components/SiteHeader.component",
      "fullName": "SiteHeader",
      "id": "0995j0000004OmrAAE",
      "lastModifiedById": "0055j000004hAriAAE",
      "lastModifiedByName": "Subhash Panchani",
      "lastModifiedDate": "2023-07-14T03:49:31.000Z",
      "manageableState": "unmanaged",
      "type": "ApexComponent"
    },
    {
      "createdById": "0055j000004hAriAAE",
      "createdByName": "Subhash Panchani",
      "createdDate": "2023-07-14T03:49:31.000Z",
      "fileName": "components/SiteLogin.component",
      "fullName": "SiteLogin",
      "id": "0995j0000004OmtAAE",
      "lastModifiedById": "0055j000004hAriAAE",
      "lastModifiedByName": "Subhash Panchani",
      "lastModifiedDate": "2023-07-14T03:49:31.000Z",
      "manageableState": "unmanaged",
      "type": "ApexComponent"
    },
    {
      "createdById": "0055j000004hAriAAE",
      "createdByName": "Subhash Panchani",
      "createdDate": "2025-06-12T09:23:54.000Z",
      "fileName": "components/et4ae5__pageMessages.component",
      "fullName": "et4ae5__pageMessages",
      "id": "099Ip0000004D8VIAU",
      "lastModifiedById": "0055j000004hAriAAE",
      "lastModifiedByName": "Subhash Panchani",
      "lastModifiedDate": "2025-06-12T09:26:02.000Z",
      "manageableState": "installed",
      "namespacePrefix": "et4ae5",
      "type": "ApexComponent"
    },
    {
      "createdById": "0055j000004hAriAAE",
      "createdByName": "Subhash Panchani",
      "createdDate": "2025-06-12T09:23:54.000Z",
      "fileName": "components/et4ae5__NotificationBanner.component",
      "fullName": "et4ae5__NotificationBanner",
      "id": "099Ip0000004D8SIAU",
      "lastModifiedById": "0055j000004hAriAAE",
      "lastModifiedByName": "Subhash Panchani",
      "lastModifiedDate": "2025-06-12T09:26:00.000Z",
      "manageableState": "installed",
      "namespacePrefix": "et4ae5",
      "type": "ApexComponent"
    },
    {
      "createdById": "0055j000004hAriAAE",
      "createdByName": "Subhash Panchani",
      "createdDate": "2025-06-12T09:23:54.000Z",
      "fileName": "components/et4ae5__MultiselectPicklist.component",
      "fullName": "et4ae5__MultiselectPicklist",
      "id": "099Ip0000004D8RIAU",
      "lastModifiedById": "0055j000004hAriAAE",
      "lastModifiedByName": "Subhash Panchani",
      "lastModifiedDate": "2025-06-12T09:25:59.000Z",
      "manageableState": "installed",
      "namespacePrefix": "et4ae5",
      "type": "ApexComponent"
    },
    {
      "createdById": "0055j000004hAriAAE",
      "createdByName": "Subhash Panchani",
      "createdDate": "2025-05-08T05:04:02.000Z",
      "fileName": "components/signature__PreviewPDF.component",
      "fullName": "signature__PreviewPDF",
      "id": "099Ip0000004D6nIAE",
      "lastModifiedById": "0055j000004hAriAAE",
      "lastModifiedByName": "Subhash Panchani",
      "lastModifiedDate": "2025-05-08T05:05:52.000Z",
      "manageableState": "installed",
      "namespacePrefix": "signature",
      "type": "ApexComponent"
    },
    {
      "createdById": "0055j000004ojWLAAY",
      "createdByName": "iTechCloud Sales",
      "createdDate": "2022-02-09T14:35:17.000Z",
      "fileName": "components/CHANNEL_ORDERS__Autocomplete.component",
      "fullName": "CHANNEL_ORDERS__Autocomplete",
      "id": "0995j000000YArqAAG",
      "lastModifiedById": "0055j000004ojWNAAY",
      "lastModifiedByName": "SFDC Channel Order",
      "lastModifiedDate": "2022-12-09T02:03:23.000Z",
      "manageableState": "installed",
      "namespacePrefix": "CHANNEL_ORDERS",
      "type": "ApexComponent"
    },
    {
      "createdById": "0055j000004hAriAAE",
      "createdByName": "Subhash Panchani",
      "createdDate": "2025-06-12T09:23:54.000Z",
      "fileName": "components/et4ae5__TypeAheadPillBox.component",
      "fullName": "et4ae5__TypeAheadPillBox",
      "id": "099Ip0000004D8TIAU",
      "lastModifiedById": "0055j000004hAriAAE",
      "lastModifiedByName": "Subhash Panchani",
      "lastModifiedDate": "2025-06-12T09:26:00.000Z",
      "manageableState": "installed",
      "namespacePrefix": "et4ae5",
      "type": "ApexComponent"
    },
    {
      "createdById": "0055j000004hAriAAE",
      "createdByName": "Subhash Panchani",
      "createdDate": "2025-05-08T05:04:02.000Z",
      "fileName": "components/signature__LightningSignature.component",
      "fullName": "signature__LightningSignature",
      "id": "099Ip0000004D6kIAE",
      "lastModifiedById": "0055j000004hAriAAE",
      "lastModifiedByName": "Subhash Panchani",
      "lastModifiedDate": "2025-05-08T05:04:02.000Z",
      "manageableState": "installed",
      "namespacePrefix": "signature",
      "type": "ApexComponent"
    },
    {
      "createdById": "0055j000004hAriAAE",
      "createdByName": "Subhash Panchani",
      "createdDate": "2025-06-12T09:23:54.000Z",
      "fileName": "components/et4ae5__MarketingCloudActions.component",
      "fullName": "et4ae5__MarketingCloudActions",
      "id": "099Ip0000004D8QIAU",
      "lastModifiedById": "0055j000004hAriAAE",
      "lastModifiedByName": "Subhash Panchani",
      "lastModifiedDate": "2025-06-12T09:25:59.000Z",
      "manageableState": "installed",
      "namespacePrefix": "et4ae5",
      "type": "ApexComponent"
    },
    {
      "createdById": "0055j000004hAriAAE",
      "createdByName": "Subhash Panchani",
      "createdDate": "2025-06-12T09:23:54.000Z",
      "fileName": "components/et4ae5__ETHeader.component",
      "fullName": "et4ae5__ETHeader",
      "id": "099Ip0000004D8OIAU",
      "lastModifiedById": "0055j000004hAriAAE",
      "lastModifiedByName": "Subhash Panchani",
      "lastModifiedDate": "2025-06-12T09:23:54.000Z",
      "manageableState": "installed",
      "namespacePrefix": "et4ae5",
      "type": "ApexComponent"
    },
    {
      "createdById": "0055j000004hAriAAE",
      "createdByName": "Subhash Panchani",
      "createdDate": "2025-06-12T09:23:54.000Z",
      "fileName": "components/et4ae5__MCEmailPicker.component",
      "fullName": "et4ae5__MCEmailPicker",
      "id": "099Ip0000004D8PIAU",
      "lastModifiedById": "0055j000004hAriAAE",
      "lastModifiedByName": "Subhash Panchani",
      "lastModifiedDate": "2025-06-12T09:25:55.000Z",
      "manageableState": "installed",
      "namespacePrefix": "et4ae5",
      "type": "ApexComponent"
    },
    {
      "createdById": "0055j000004hAriAAE",
      "createdByName": "Subhash Panchani",
      "createdDate": "2023-07-14T03:49:31.000Z",
      "fileName": "components/SiteFooter.component",
      "fullName": "SiteFooter",
      "id": "0995j0000004OmsAAE",
      "lastModifiedById": "0055j000004hAriAAE",
      "lastModifiedByName": "Subhash Panchani",
      "lastModifiedDate": "2023-07-14T03:49:31.000Z",
      "manageableState": "unmanaged",
      "type": "ApexComponent"
    },
    {
      "createdById": "0055j000004hAriAAE",
      "createdByName": "Subhash Panchani",
      "createdDate": "2025-05-08T05:04:02.000Z",
      "fileName": "components/signature__ExportExperiences.component",
      "fullName": "signature__ExportExperiences",
      "id": "099Ip0000004D6lIAE",
      "lastModifiedById": "0055j000004hAriAAE",
      "lastModifiedByName": "Subhash Panchani",
      "lastModifiedDate": "2025-05-08T05:05:51.000Z",
      "manageableState": "installed",
      "namespacePrefix": "signature",
      "type": "ApexComponent"
    },
    {
      "createdById": "0055j000004hAriAAE",
      "createdByName": "Subhash Panchani",
      "createdDate": "2025-06-12T09:23:54.000Z",
      "fileName": "components/et4ae5__ConfigIncludes.component",
      "fullName": "et4ae5__ConfigIncludes",
      "id": "099Ip0000004D8NIAU",
      "lastModifiedById": "0055j000004hAriAAE",
      "lastModifiedByName": "Subhash Panchani",
      "lastModifiedDate": "2025-06-12T09:23:54.000Z",
      "manageableState": "installed",
      "namespacePrefix": "et4ae5",
      "type": "ApexComponent"
    }
  ]
}